result_analytics/__init__.py
result_analytics/src/__init__.py
result_analytics/src/analytics.py
result_analytics/src/pdf_analyser.py
result_analytics/src/scrapping.py
result_analytics/src/moguls/__init__.py
result_analytics/src/moguls/athlete_result.py
result_analytics/src/moguls/pdf_analyser.py
result_analytics/src/moguls/scrapper.py
result_analytics/tests/moguls/__init__.py
result_analytics/tests/moguls/test_mogul_athlete_result.py
result_analytics/tests/moguls/test_mogul_pdf_analyser.py
result_analytics/tests/moguls/test_mogul_scrapper.py
result_analytics-1.6.3.dist-info/LICENSE
result_analytics-1.6.3.dist-info/METADATA
result_analytics-1.6.3.dist-info/WHEEL
result_analytics-1.6.3.dist-info/top_level.txt
result_analytics-1.6.3.dist-info/RECORD
