Metadata-Version: 2.1
Name: result-analytics
Version: 1.6.3
Summary: A simple project to extract data from PDFs and analyse them.
Home-page: https://github.com/tomjeannesson/result-analytics
Download-URL: https://github.com/tomjeannesson/result-analytics/archive/refs/tags/v1.6.3.tar.gz
Author: Mateo & Tom Jeannesson
Author-email: tomjeannesson@gmail.com
License: MIT
Keywords: Sport,Ski,Result,Analytics,Moguls
Classifier: Development Status :: 4 - Beta
Classifier: Intended Audience :: Developers
Classifier: Topic :: Software Development :: Build Tools
Classifier: License :: OSI Approved :: MIT License
Classifier: Programming Language :: Python :: 3.11
License-File: LICENSE
Requires-Dist: PyPDF2 >=3.0.0
Requires-Dist: pandas
Requires-Dist: requests
Requires-Dist: beautifulsoup4 >=4.12.2
